linuxforhealth/x12/__init__.py
linuxforhealth/x12/api.py
linuxforhealth/x12/cli.py
linuxforhealth/x12/config.py
linuxforhealth/x12/encoding.py
linuxforhealth/x12/io.py
linuxforhealth/x12/models.py
linuxforhealth/x12/parsing.py
linuxforhealth/x12/support.py
linuxforhealth/x12/validators.py
linuxforhealth/x12/v4010/__init__.py
linuxforhealth/x12/v4010/segments.py
linuxforhealth/x12/v4010/validators.py
linuxforhealth/x12/v4010/x12_837_004010X096A1/__init__.py
linuxforhealth/x12/v4010/x12_837_004010X096A1/loops.py
linuxforhealth/x12/v4010/x12_837_004010X096A1/parsing.py
linuxforhealth/x12/v4010/x12_837_004010X096A1/segments.py
linuxforhealth/x12/v4010/x12_837_004010X096A1/transaction_set.py
linuxforhealth/x12/v4010/x12_837_004010X098A1/__init__.py
linuxforhealth/x12/v4010/x12_837_004010X098A1/loops.py
linuxforhealth/x12/v4010/x12_837_004010X098A1/parsing.py
linuxforhealth/x12/v4010/x12_837_004010X098A1/segments.py
linuxforhealth/x12/v4010/x12_837_004010X098A1/transaction_set.py
linuxforhealth/x12/v5010/__init__.py
linuxforhealth/x12/v5010/segments.py
linuxforhealth/x12/v5010/validators.py
linuxforhealth/x12/v5010/x12_270_005010X279A1/__init__.py
linuxforhealth/x12/v5010/x12_270_005010X279A1/loops.py
linuxforhealth/x12/v5010/x12_270_005010X279A1/parsing.py
linuxforhealth/x12/v5010/x12_270_005010X279A1/segments.py
linuxforhealth/x12/v5010/x12_270_005010X279A1/transaction_set.py
linuxforhealth/x12/v5010/x12_271_005010X279A1/__init__.py
linuxforhealth/x12/v5010/x12_271_005010X279A1/loops.py
linuxforhealth/x12/v5010/x12_271_005010X279A1/parsing.py
linuxforhealth/x12/v5010/x12_271_005010X279A1/segments.py
linuxforhealth/x12/v5010/x12_271_005010X279A1/transaction_set.py
linuxforhealth/x12/v5010/x12_276_005010X212/__init__.py
linuxforhealth/x12/v5010/x12_276_005010X212/loops.py
linuxforhealth/x12/v5010/x12_276_005010X212/parsing.py
linuxforhealth/x12/v5010/x12_276_005010X212/segments.py
linuxforhealth/x12/v5010/x12_276_005010X212/transaction_set.py
linuxforhealth_x12-0.57.0.dist-info/LICENSE
linuxforhealth_x12-0.57.0.dist-info/METADATA
linuxforhealth_x12-0.57.0.dist-info/WHEEL
linuxforhealth_x12-0.57.0.dist-info/entry_points.txt
linuxforhealth_x12-0.57.0.dist-info/top_level.txt
linuxforhealth_x12-0.57.0.dist-info/RECORD
