Metadata-Version: 2.1
Name: linuxforhealth-x12
Version: 0.57.0
Summary: LinuxForHealth x12 streams ASC 5010 X12 health care transactions into Pydantic Models for a pleasant pythonic parsing experience! Integration options include REST endpoints, CLI (command line), or direct access using the Python SDK
License: Apache 2.0
Classifier: Development Status :: 4 - Beta
Classifier: License :: OSI Approved :: Apache Software License
Classifier: Operating System :: OS Independent
Classifier: Programming Language :: Python :: 3.8
Classifier: Programming Language :: Python :: 3.9
Classifier: Intended Audience :: Healthcare Industry
Classifier: Intended Audience :: Developers
Requires-Python: >=3.8
License-File: LICENSE
Requires-Dist: pydantic (>=1.9)
Requires-Dist: python-dotenv (>=0.19.0)
Provides-Extra: api
Requires-Dist: fastapi (>=0.78.0) ; extra == 'api'
Requires-Dist: uvicorn[standard] (>=0.17.0) ; extra == 'api'
Requires-Dist: requests (>=2.27.0) ; extra == 'api'
Provides-Extra: dev
Requires-Dist: black (>=22.3.0) ; extra == 'dev'
Requires-Dist: pre-commit (>=2.14.1) ; extra == 'dev'
Requires-Dist: pytest (>=7.1.0) ; extra == 'dev'
